uvarint/__init__.py
uvarint/py.typed
uvarint-1.2.0.dist-info/LICENSE.MIT
uvarint-1.2.0.dist-info/METADATA
uvarint-1.2.0.dist-info/WHEEL
uvarint-1.2.0.dist-info/top_level.txt
uvarint-1.2.0.dist-info/RECORD
