Metadata-Version: 2.1
Name: uvarint
Version: 1.2.0
Summary: Unsigned variable-length integers
Home-page: https://github.com/matheusmoreira/uvarint.py
Author: Matheus Afonso Martins Moreira
Author-email: matheus.a.m.moreira@gmail.com
License: UNKNOWN
Platform: UNKNOWN
Classifier: Programming Language :: Python :: 3
Classifier: Programming Language :: Python :: 3.6
Classifier: Programming Language :: Python :: 3.7
Classifier: Programming Language :: Python :: 3.8
Classifier: Programming Language :: Python :: 3 :: Only
Classifier: License :: OSI Approved :: MIT License
Classifier: Operating System :: OS Independent
Classifier: Topic :: Software Development :: Libraries
Classifier: Topic :: Software Development :: Libraries :: Python Modules
Classifier: Typing :: Typed
Requires-Python: >=3.6
